norn/__init__.py
norn-0.0.1.dist-info/LICENSE
norn-0.0.1.dist-info/WHEEL
norn-0.0.1.dist-info/METADATA
norn-0.0.1.dist-info/RECORD
