Metadata-Version: 2.1
Name: norn
Version: 0.0.1
Summary: reStructuredText based job-manager.
Author-email: Kazuya Takei <myself@attakei.net>
Classifier: Development Status :: 1 - Planning
Classifier: License :: OSI Approved :: Apache Software License
Requires-Dist: docutils >=0.20.1
Project-URL: Home, https://attakei-lab.github.io/norn
